CHANGES.txt
LICENSE
MANIFEST.in
README.rst
setup.py
esrf/__init__.py
esrf/bibtex.py
esrf/protocols.conf
esrf/protocols/__init__.py
esrf/protocols/protocol_monitor_ispyb_esrf.py
esrf/tests/__init__.py
esrf/tests/test_esrf_utils_icat.py
esrf/tests/test_esrf_utils_icat_execution.py
esrf/tests/test_esrf_utils_ispyb.py
esrf/tests/test_esrf_utils_ispyb_execution.py
esrf/tests/test_esrf_utils_path.py
esrf/utils/ESRFMetadataManagerClient.py
esrf/utils/__init__.py
esrf/utils/em.py
esrf/utils/esrf_launch_workflow.py
esrf/utils/esrf_utils_icat.py
esrf/utils/esrf_utils_ispyb.py
esrf/utils/esrf_utils_path.py
scipion_em_esrf.egg-info/PKG-INFO
scipion_em_esrf.egg-info/SOURCES.txt
scipion_em_esrf.egg-info/dependency_links.txt
scipion_em_esrf.egg-info/requires.txt
scipion_em_esrf.egg-info/top_level.txt