Metadata-Version: 1.0
Name: scipion-em-esrf
Version: 1.0.2
Summary: Esrf's ISPyB monitor for Scipion
Home-page: https://github.com/scipion-em/scipion-em-esrf
Author: I2PC
Author-email: scipion@cnb.csic.es
License: UNKNOWN
Keywords: scipion cryoem imageprocessing scipion-2.0
Platform: UNKNOWN
